{"NumDays":4,"NumRooms":8,"GroupsSizes":[8,2,9,5,2,3,3,1,2,2,1,1,8,2,4,2,5,1,1,1,2,1,1],"RoomCapacity":[2,7,10,1,1,1,1,2],"GroupsDemands":[{"Item1":1,"Item2":1},{"Item1":2,"Item2":1},{"Item1":3,"Item2":1},{"Item1":4,"Item2":1},{"Item1":5,"Item2":1},{"Item1":6,"Item2":1},{"Item1":7,"Item2":1},{"Item1":2,"Item2":2},{"Item1":3,"Item2":2},{"Item1":4,"Item2":2},{"Item1":5,"Item2":2},{"Item1":7,"Item2":2},{"Item1":8,"Item2":2},{"Item1":9,"Item2":2},{"Item1":10,"Item2":2},{"Item1":10,"Item2":3},{"Item1":11,"Item2":3},{"Item1":12,"Item2":3},{"Item1":13,"Item2":3},{"Item1":14,"Item2":3},{"Item1":15,"Item2":3},{"Item1":16,"Item2":3},{"Item1":17,"Item2":3},{"Item1":18,"Item2":3},{"Item1":10,"Item2":4},{"Item1":11,"Item2":4},{"Item1":12,"Item2":4},{"Item1":13,"Item2":4},{"Item1":15,"Item2":4},{"Item1":16,"Item2":4},{"Item1":18,"Item2":4},{"Item1":19,"Item2":4},{"Item1":20,"Item2":4},{"Item1":21,"Item2":4},{"Item1":22,"Item2":4}],"InitialAllocation":[{"Item1":0,"Item2":2}]}